{
    "recipe": {
        "title": "Avocado Daiquiri ",
        "ingredients": [
            "2 ounces light rum",
            "2 ounces gold rum",
            "1/2 ounce fresh lemon juice",
            "1/2 ounce fresh lime juice",
            "2 ounces simple syrup",
            "1/4 medium-ripe avocado, peeled and pitted",
            "1/2 ounce half-and-half",
            "1 1/2 cups ice"
        ],
        "instructions": [
            "Combine ingredients in blender and blend on high until just smooth, about 20 seconds. Divide mixture between two cocktail glasses and serve."
        ],
        "picture_link": "https://assets.epicurious.com/photos/560dd788f3a00aeb2f1d27fe/6:4/w_274%2Ch_169/235568.jpg",
        "color": 11673818
    }
}