{
    "recipe": {
        "title": "Brainy Breakfast ",
        "ingredients": [
            "1 cup greek yogurt",
            "1 tablespoon honey",
            "1 small apple, cored and chopped",
            "1/2 cup mixed berries",
            "2 tablespoons chopped walnuts",
            "2 tablespoons flax seeds, ground or whole",
            "1/2 teaspoon ground cinnamon"
        ],
        "instructions": [
            "Place all ingredients in a bowl and stir to combine."
        ],
        "picture_link": "https://assets.epicurious.com/photos/54cadc8f1f13bb9b2edfa657/6:4/w_274%2Ch_169/51262410_brainy-breakfast_6x4_1x1.jpg"
    }
}