{
    "recipe": {
        "title": "Cucumbers with Ajo Blanco Sauce ",
        "ingredients": [
            "5 mini seedless or Persian cucumbers (about 12 oz.)",
            "Kosher salt",
            "3 tsp. sherry vinegar or red wine vinegar, divided",
            "3/4 cup blanched almonds, divided",
            "1 garlic clove, finely grated",
            "1/2 cup extra-virgin olive oil",
            "Flaky sea salt"
        ],
        "instructions": [
            "Preheat oven to 350\u00b0F. Cut cucumbers about 1\" thick on a steep diagonal and place in a medium bowl. Add a large pinch of kosher salt and 2 tsp. vinegar and toss to combine; let marinate 10 minutes. Pour off any liquid that is released.",
            "Toast 1/4 cup almonds on a rimmed baking sheet, tossing once, until golden, about 5 minutes. Let cool, then coarsely chop. Set aside.",
            "Blend garlic, oil, remaining 1 tsp. vinegar, remaining \u00bd cup almonds, and 1/2 cup ice water in a blender until smooth and creamy, about 2 minutes; season generously with salt.",
            "Divide sauce among plates and top with cucumber salad and chopped almonds. Sprinkle with flaky sea salt.",
            "Do Ahead Sauce can be made 1 day ahead. Cover and chill.",
            "Sauce can be made 1 day ahead. Cover and chill."
        ],
        "picture_link": "https://assets.epicurious.com/photos/5bc4da2589c45f2d1b394787/6:4/w_274%2Ch_169/cucumbers-with-ajo-blanco-sauce-recipe-BA-101518.jpg"
    }
}