{
    "recipe": {
        "title": "Guacamole for Lindsay ",
        "ingredients": [
            "3 firm but ripe Hass avocados, halved, pitted, peeled, and cut into 1/2-inch pieces",
            "3 tablespoons finely chopped fresh cilantro",
            "2 tablespoons fresh lime juice",
            "1/2 jalape\u00f1o pepper, seeded and finely chopped",
            "1 garlic clove, finely chopped",
            "1/4 teaspoon ground cumin",
            "Kosher salt"
        ],
        "instructions": [
            "In a large bowl, gently fold the avocados, cilantro, lime juice, jalape\u00f1os, garlic, and cumin together. Season to taste with salt.",
            "In a large bowl, gently fold the avocados, cilantro, lime juice, jalape\u00f1os, garlic, and cumin together. Season to taste with salt."
        ],
        "picture_link": null
    }
}