{
    "recipe": {
        "title": "Island Rum Punch ",
        "ingredients": [
            "(12-oz) can guava nectar",
            "1 1/2 cups fresh orange juice",
            "1 1/2 cups unsweetened pineapple juice",
            "1 1/2 cups rum",
            "1/2 cup fresh lime juice",
            "8 drops Angostura bitters",
            "Freshly grated nutmeg to taste",
            "Garnish: lime slices"
        ],
        "instructions": [
            "Stir together all ingredients except nutmeg in a pitcher. Serve over ice, sprinkled with a bit of nutmeg."
        ],
        "picture_link": null
    }
}