{
    "recipe": {
        "title": "Jalape\u00f1o Cheese Grits ",
        "ingredients": [
            "1 cup stone-ground white corn grits",
            "1 jalape\u00f1o pepper",
            "3 tablespoons butter",
            "2 tablespoons mascarpone or cream cheese",
            "1/4 cup grated Edam cheese",
            "Salt"
        ],
        "instructions": [
            "1. Heat 4 cups of water in a large heavy-bottomed pot over high heat until it comes to a boil. Slowly pour in the grits while whisking constantly. Reduce the heat to low, cover, and cook, stirring occasionally with a wooden spoon, for about 20 minutes.",
            "2. While the grits are cooking, pan-roast the jalape\u00f1o pepper in a small skillet over high heat until the skin is brown and blistered. Cut the pepper in half lengthwise and remove the skin and the seeds from the pepper and discard. Mince the flesh and add it to the pot of grits.",
            "3. Remove the pot from the heat and fold in the butter, mascarpone, and Edam cheese. Season with salt."
        ],
        "picture_link": "https://assets.epicurious.com/photos/54b30a1211c5d6af478b8fe2/6:4/w_274%2Ch_169/356851_jalapeno-cheese-grits_1x1.jpg"
    }
}