{
    "recipe": {
        "title": "Ranchero Sauce ",
        "ingredients": [
            "1 tablespoon butter",
            "1/2 cup chopped onion",
            "1/2 cup chopped green bell pepper",
            "1 jalape\u00f1o pepper, chopped",
            "1 large garlic clove, chopped",
            "1 1/2 teaspoons ground cumin",
            "1/4 teaspoon cayenne pepper",
            "2 cups canned chicken broth",
            "1 8-ounce can tomato sauce",
            "1/4 cup chopped fresh cilantro"
        ],
        "instructions": [
            "Melt butter in heavy large skillet over medium heat. Add next 6 ingredients and saut\u00e9 until vegetables are soft, about 5 minutes. Add broth and tomato sauce and cook until sauce thickens and reduces to 1 1/2 cups, stirring frequently, about 20 minutes. Mix in cilantro.",
            "Melt butter in heavy large skillet over medium heat. Add next 6 ingredients and saut\u00e9 until vegetables are soft, about 5 minutes. Add broth and tomato sauce and cook until sauce thickens and reduces to 1 1/2 cups, stirring frequently, about 20 minutes. Mix in cilantro."
        ],
        "picture_link": "https://assets.epicurious.com/photos/579fa0c33a12dd9d5602406c/6:4/w_274%2Ch_169/ranchero-sauce.jpg"
    }
}