{
    "recipe": {
        "title": "Slow-Cooked Winter Squash with Sage and Thyme ",
        "ingredients": [
            "1 lb. delicata or acorn squash, halved lengthwise, seeds removed, sliced crosswise 1/2\" thick",
            "1/2 head of garlic",
            "2 sprigs sage",
            "2 sprigs thyme",
            "1/2 cup extra-virgin olive oil",
            "3/4 tsp. kosher salt",
            "1 Tbsp. white wine vinegar"
        ],
        "instructions": [
            "Place a rack in middle of oven and preheat to 350\u00b0F. Toss squash, garlic, sage, thyme, oil, and salt in a shallow 2-qt. baking dish to combine.",
            "Turn garlic cut side down, then roast vegetables, tossing 2 or 3 times, until golden brown, very tender, and edges and cut sides are crisp, 60\u201370 minutes. Let cool slightly, then add vinegar and toss to coat."
        ],
        "picture_link": "https://assets.epicurious.com/photos/5ba00b2bb1754b7eaace5136/6:4/w_274%2Ch_169/slow-cooked-winter-squash-with-sage-and-thyme-recipe-BA-091718.jpg",
        "color": 386001
    }
}